crink/main.py
crink-0.0.0.dist-info/METADATA
crink-0.0.0.dist-info/WHEEL
crink-0.0.0.dist-info/top_level.txt
crink-0.0.0.dist-info/RECORD
