Metadata-Version: 2.1
Name: crink
Version: 0.0.0
Summary: A work presented to Spring Thing 2025.
